{
	"name": "ETL",
	"properties": {
		"activities": [
			{
				"name": "Script1",
				"type": "Script",
				"dependsOn": [],
				"policy": {
					"timeout": "0.12:00:00",
					"retry": 0,
					"retryIntervalInSeconds": 30,
					"secureOutput": false,
					"secureInput": false
				},
				"userProperties": [],
				"linkedServiceName": {
					"referenceName": "ls_sql_dw_entel",
					"type": "LinkedServiceReference"
				},
				"typeProperties": {
					"scripts": [
						{
							"type": "NonQuery",
							"text": "delete from gold.dim_fecha;\nDELETE  from gold.dim_numero;\nDELETE from gold.dim_radiobase;\ndelete from gold.dim_registro;\ndelete from gold.dim_servicio;\ndelete from gold.hechos_datos;\ndelete from gold.hechos_llamadas;"
						}
					],
					"scriptBlockExecutionTimeout": "02:00:00"
				}
			},
			{
				"name": "dimServicio",
				"type": "ExecuteDataFlow",
				"dependsOn": [
					{
						"activity": "Script1",
						"dependencyConditions": [
							"Succeeded"
						]
					}
				],
				"policy": {
					"timeout": "0.12:00:00",
					"retry": 0,
					"retryIntervalInSeconds": 30,
					"secureOutput": false,
					"secureInput": false
				},
				"userProperties": [],
				"typeProperties": {
					"dataflow": {
						"referenceName": "df_gold_dim_servicio",
						"type": "DataFlowReference"
					},
					"compute": {
						"coreCount": 8,
						"computeType": "General"
					},
					"traceLevel": "Fine"
				}
			},
			{
				"name": "DimRegistro",
				"type": "ExecuteDataFlow",
				"dependsOn": [
					{
						"activity": "dimServicio",
						"dependencyConditions": [
							"Succeeded"
						]
					}
				],
				"policy": {
					"timeout": "0.12:00:00",
					"retry": 0,
					"retryIntervalInSeconds": 30,
					"secureOutput": false,
					"secureInput": false
				},
				"userProperties": [],
				"typeProperties": {
					"dataflow": {
						"referenceName": "df_gold_dim_registro",
						"type": "DataFlowReference"
					},
					"compute": {
						"coreCount": 8,
						"computeType": "General"
					},
					"traceLevel": "Fine"
				}
			},
			{
				"name": "DimRbs",
				"type": "ExecuteDataFlow",
				"dependsOn": [
					{
						"activity": "DimRegistro",
						"dependencyConditions": [
							"Succeeded"
						]
					}
				],
				"policy": {
					"timeout": "0.12:00:00",
					"retry": 0,
					"retryIntervalInSeconds": 30,
					"secureOutput": false,
					"secureInput": false
				},
				"userProperties": [],
				"typeProperties": {
					"dataflow": {
						"referenceName": "df_gold_dim_rbs",
						"type": "DataFlowReference"
					},
					"compute": {
						"coreCount": 8,
						"computeType": "General"
					},
					"traceLevel": "Fine"
				}
			},
			{
				"name": "DimNumero",
				"type": "ExecuteDataFlow",
				"dependsOn": [
					{
						"activity": "DimRbs",
						"dependencyConditions": [
							"Succeeded"
						]
					}
				],
				"policy": {
					"timeout": "0.12:00:00",
					"retry": 0,
					"retryIntervalInSeconds": 30,
					"secureOutput": false,
					"secureInput": false
				},
				"userProperties": [],
				"typeProperties": {
					"dataflow": {
						"referenceName": "df_gold_dim_numero",
						"type": "DataFlowReference"
					},
					"compute": {
						"coreCount": 8,
						"computeType": "General"
					},
					"traceLevel": "Fine"
				}
			},
			{
				"name": "DimFecha",
				"type": "ExecuteDataFlow",
				"dependsOn": [
					{
						"activity": "DimNumero",
						"dependencyConditions": [
							"Succeeded"
						]
					}
				],
				"policy": {
					"timeout": "0.12:00:00",
					"retry": 0,
					"retryIntervalInSeconds": 30,
					"secureOutput": false,
					"secureInput": false
				},
				"userProperties": [],
				"typeProperties": {
					"dataflow": {
						"referenceName": "df_gold_dim_fecha",
						"type": "DataFlowReference"
					},
					"compute": {
						"coreCount": 8,
						"computeType": "General"
					},
					"traceLevel": "Fine"
				}
			},
			{
				"name": "hechosLlamadas",
				"type": "ExecuteDataFlow",
				"dependsOn": [
					{
						"activity": "DimFecha",
						"dependencyConditions": [
							"Succeeded"
						]
					}
				],
				"policy": {
					"timeout": "0.12:00:00",
					"retry": 0,
					"retryIntervalInSeconds": 30,
					"secureOutput": false,
					"secureInput": false
				},
				"userProperties": [],
				"typeProperties": {
					"dataflow": {
						"referenceName": "df_gold_hechos_llamadas",
						"type": "DataFlowReference"
					},
					"compute": {
						"coreCount": 8,
						"computeType": "General"
					},
					"traceLevel": "Fine"
				}
			}
		],
		"folder": {
			"name": "Gold"
		},
		"annotations": []
	}
}